{
    "entreprise": {
        "nom": "Porte Bonheur",
        "slogan": "Votre succès est notre mission",
        "telephone": "+225 0574404978",
        "email": "bamorobusiness@gmail.com",
        "adresse": "Abidjan, Côte d'Ivoire",
        "logo": "https://via.placeholder.com/200x80/2563eb/ffffff?text=Porte+Bonheur",
        "favicon": "images/favicon.ico",
        "couleurs": {
            "primaire": "#2563eb",
            "secondaire": "#7c3aed",
            "accent": "#f59e0b",
            "texte": "#1f2937",
            "fond": "#f9fafb"
        },
        "reseaux": {
            "facebook": "",
            "instagram": "",
            "linkedin": ""
        }
    },
    "whatsapp": {
        "numero": "2250574404978",
        "messageDefaut": "Bonjour, je suis intéressé par : "
    },
    "seo": {
        "titre": "Porte Bonheur - Formations & Services Premium",
        "description": "Découvrez nos formations professionnelles et services de coaching pour réussir votre business",
        "motsCles": "formation, coaching, business, développement personnel, Abidjan"
    },
    "produits": [
        {
            "id": 1,
            "actif": true,
            "vedette": true,
            "nom": "Formation Marketing Digital",
            "slug": "formation-marketing-digital",
            "categorie": "formations",
            "prix": 150000,
            "devise": "FCFA",
            "reduction": 0,
            "images": [
                "https://images.unsplash.com/photo-1552664730-d307ca884978?w=800&h=600&fit=crop",
                "https://images.unsplash.com/photo-1519389950473-47ba0277781c?w=800&h=600&fit=crop",
                "https://images.unsplash.com/photo-1522071820081-009f0129c71c?w=800&h=600&fit=crop"
            ],
            "descriptionCourte": "Maîtrisez les stratégies du marketing digital en 8 semaines",
            "descriptionComplete": "Cette formation complète vous permettra de devenir un expert du marketing digital. Vous apprendrez les techniques avancées de SEO, publicité Facebook/Instagram, email marketing et création de contenu viral.",
            "avantages": [
                "Certification professionnelle reconnue",
                "8 semaines de formation intensive",
                "Suivi personnalisé par un mentor",
                "Accès à vie aux ressources",
                "Groupe privé d'entraide"
            ],
            "caracteristiques": [
                {
                    "nom": "Durée",
                    "valeur": "8 semaines"
                },
                {
                    "nom": "Format",
                    "valeur": "100% en ligne"
                },
                {
                    "nom": "Niveau",
                    "valeur": "Débutant à Intermédiaire"
                },
                {
                    "nom": "Langue",
                    "valeur": "Français"
                }
            ],
            "tags": [
                "marketing",
                "digital",
                "formation"
            ],
            "messageWhatsapp": "Bonjour ! Je suis intéressé par la Formation Marketing Digital.",
            "produitsLies": [
                2,
                3
            ],
            "dateAjout": "2024-01-15",
            "vues": 0,
            "commandes": 0
        }
    ],
    "temoignages": [
        {
            "id": 1,
            "nom": "Aminata K.",
            "entreprise": "AK Cosmétiques",
            "photo": "https://i.pravatar.cc/150?img=1",
            "note": 5,
            "texte": "Excellente formation !",
            "produitId": 1
        }
    ],
    "categories": [
        {
            "id": "formations",
            "nom": "Formations",
            "icone": "🎓",
            "description": "Formations professionnelles en ligne"
        },
        {
            "id": "coaching",
            "nom": "Coaching",
            "icone": "🎯",
            "description": "Accompagnement personnalisé"
        },
        {
            "id": "services",
            "nom": "Services",
            "icone": "💼",
            "description": "Services sur-mesure pour votre business"
        }
    ],
    "parametres": {
        "produitsParPage": 6,
        "produitsVedettesMax": 3,
        "afficherPrix": true,
        "afficherReduction": true,
        "activerRecherche": true,
        "activerFiltre": true,
        "activerTri": true
    }
}
